.bumpversion.cfg
.editorconfig
.pre-commit-config.yaml
AUTHORS.rst
CHANGELOG.rst
CONTRIBUTING.rst
LICENSE
README.rst
ase-stubs/__init__.pyi
ase-stubs/atom.pyi
ase-stubs/atoms.pyi
ase-stubs/cell.pyi
ase-stubs/geometry/geometry.pyi
ase_stubs-0.0.2.dist-info/LICENSE
ase_stubs-0.0.2.dist-info/METADATA
ase_stubs-0.0.2.dist-info/WHEEL
ase_stubs-0.0.2.dist-info/RECORD
