Metadata-Version: 2.1
Name: ase-stubs
Version: 0.0.2
Summary: Stub files for the Atomic Simulation Environment package.
Home-page: https://gitlab.com/ugognw/python-comp-chem-utils
License: LGPL-2.1-or-later
Author: Ugochukwu Nwosu
Author-email: ugognw@gmail.com
Requires-Python: >=3.10,<3.12
Classifier: Development Status :: 5 - Production/Stable
Classifier: Intended Audience :: Developers
Classifier: License :: OSI Approved
Classifier: License :: OSI Approved :: GNU Lesser General Public License v2 or later (LGPLv2+)
Classifier: Programming Language :: Python :: 3
Classifier: Programming Language :: Python :: 3.10
Classifier: Programming Language :: Python :: 3.11
Classifier: Topic :: Software Development
Classifier: Typing :: Stubs Only
Requires-Dist: ase (>=3.22.1,<4.0.0)
Project-URL: Repository, https://gitlab.com/ugognw/python-comp-chem-utils
